poetryize/__init__.py
poetryize/poetryize.py
poetryize-1.0.1.dist-info/LICENSE
poetryize-1.0.1.dist-info/METADATA
poetryize-1.0.1.dist-info/WHEEL
poetryize-1.0.1.dist-info/entry_points.txt
poetryize-1.0.1.dist-info/RECORD
